wombo/__init__.py
wombo/base_client/__init__.py
wombo/base_client/dream.py
wombo/base_client/session.py
wombo/base_client/styles.py
wombo/clients/__init__.py
wombo/clients/async_dream.py
wombo/clients/dream.py
wombo/exceptions.py
wombo/models/__init__.py
wombo/models/image.py
wombo/models/style.py
wombo/models/task.py
wombo/types.py
wombo/utils.py
pywombo-0.1.1.dist-info/LICENSE
pywombo-0.1.1.dist-info/METADATA
pywombo-0.1.1.dist-info/WHEEL
pywombo-0.1.1.dist-info/RECORD
